{"_id":"68d27590-6116-11eb-bd32-2b9b43718c33","trap":"","parent":"","message":"Спортсмены и молодые люди просто без ума от кроссовок Найк. По сути в любом виде спорта <a href=https://justnike.ru/>кроссовки Nike</a> известны и пользуются огромным спросом. Достаточно людей на прогулку одевают именно кроссы Nike. Если вы планируете обновить свой гардероб и заказать стильные кроссовки, рекомендуем сделать это в интернет-магазине Найк. \r\n \r\nНа justnike.ru размещено много разных моделей кроссовок Найк. Реально подобрать прикольный вариант на осень или приобрести парочку моделей летних кроссовок. Если вы не поклонник спортивного образа жизни, но цените удобство, вам надо рассмотреть опцию покупки кроссовок Nike. \r\n \r\nС помощью найков можно ходить в спортзал, в спортивной обуви <a href=https://justnike.ru/>Nike</a> есть возможность отлично проводить время на улице, бегать, заниматься интересующими вас видами спорта. Также кроссовки Nike можно носить и в пасмурную погоду, ну или, когда очень потеют ступни. Ведь кроссы Nike оснащены универсальной технологией, которая не пропускает влагу. Также все кроссы влагонепроницаемые и изящные, они модные и стильные! \r\n \r\nЕсли вы давно подбирали кроссовки с амортизацией, есть возможность заказать и купить кроссовки Nike Air More Uptempo. Очень пользуются спросом сегодня и мужские <a href=https://justnike.ru/>кроссовки Nike</a> Air Force 1 AF1 Low Nai Ke. Если вам по вкусу разноцветные найки, есть смысл смело заказывать Nike Air Force Skeleton Black. Девушки временами берут Nike Air Max 720 Sunset Hyper Grape Black-hyper Pink. Если вы с удовольствием носите разные кроссовки, но предпочитаете носить красивые модели, лучше найков вам не найти. \r\n \r\nДоставка всех найков производится с помощью курьеров. Организация находится по адресу г. Москва, Проспект мира 103. Оплатить товар вы можете как курьеру при получении, так и с помощью кредитки Visa или MasterCard на портале. В интернет-магазине есть контакт-центр, вы можете позвонить по телефону +7(495)642-26-83 и узнать все вопросы. \r\n \r\nОгромный каталог летних моделей кроссовок уже представлен на портале, речь идёт про сезон лето 2021. Если вы хотели бы купить новые <a href=https://justnike.ru/>кроссовки Найк</a> на лето, заходите на официальный сайт интернет-магазина Nike. На ресурсе представлены разные размеры, а сделать заказ вы можете за пять минут. \r\n \r\nТакже, сегодня на портале есть реальные скидки, которые могут привлечь любого! Если вы какое-то время хотели одевать симпатичные кроссовки Найк, вам следует выбрать какую-то позицию из текущего ассортимента. Вы можете купить как женские, так и мужские кроссовки.","name":"Jakmansher","email":"088b95207adbdbda9593edf3bdc522d4","website":"https://justnike.ru/","date":"2021-01-28T03:10:44.449Z"}