{"_id":"3f8773f0-738f-11e9-b406-3b67487bedbb","trap":"","parent":"","message":"maryland latin mass\r\nslutty cock sucker\r\nmachine sex first timers\r\nfree arabian sex videos\r\nover 30 white porn\r\nnude erotic pussy ass\r\nsimmons whitetail classic scope\r\npanama anderson naked pictures\r\n \r\n \r\nhttp://robertandanya.com/guestbook/\r\nhttp://tuk-i-tuk.ru/product/igra-loto-bingo/?msg=m25r#add-review\r\nhttp://www.xscia.org/home.php?mod=space&uid=12086\r\nhttps://small.cat/entries/206075?key=skHe%2FCCWm8cL9%2F2Jgrk4CwJkK9f3AiBTpq%2BfvMzux9A%3D\r\nhttp://megadle.ru/relise/461-datalife-engine-v101-nulled-licenziya-keygen.html\r\n \r\n \r\n<a href=https://avtokosmetika.pro/avtohimiya/aktivnaya-pena/avtoshampun-dlya-beskontaktnoy-moyki-3ton-10l/>online interacial sex free</a> \r\n<a href=https://avtokosmetika.pro/avtohimiya/aktivnaya-pena/avtoshampun-dlya-beskontaktnoy-moyki-3ton-10l/>denise ass fuck</a> \r\n<a href=http://www.home666.ca/bbs/home.php?mod=space&uid=737410>wife anal forced porn</a> \r\ntheclassicpornmovies com preview 60\r\nleg sexy stocking tgp\r\nfree xxx pics download","name":"Tab","email":"e53d8ce1090bcdadcf31afbf845bbc8f","website":"https://kaigokun.info/","date":"2019-05-11T01:51:09.946Z"}