{"_id":"a7ddb550-7ea5-11ea-9ae5-0938e0bdddf4","trap":"","parent":"","message":"Acquista maschere usa e getta - autodifesa efficace ogni giorno! ... Una maschera monouso a tre strati protegge efficacemente l'apparato respiratorio da polvere, batteri e possibili infezioni da malattie infettive. Un fermo nasale flessibile aiuta la maschera a adattarsi perfettamente al viso e gli elastici morbidi fissano comodamente la maschera senza causare irritazioni alla pelle. Le dimensioni e la densita della maschera offrono una vestibilita confortevole a lungo.... \r\n \r\nДАЛЕЕ: https://t.co/RWjWWAY56i","name":"Roberthoumb","email":"f99d9e7266df9f5aeddcfd8de2a92651","website":"https://a.aliexpress.com/_dTwaiy0","date":"2020-04-14T23:14:14.216Z"}