{"_id":"a7f0d940-0bbb-11e9-a9b2-878f92a71035","trap":"","parent":"","message":"<b>Приветствую!</b> \r\n<b>Как заработать в интернете? Есть ответ!</b> \r\nКак же приятно сидеть в уютном кресле и следить, как на электронный кошелек капают крупные суммы денег. Чтобы достичь такого результата, совсем не нужно упорно трудиться. Достаточно просто рационально использовать необходимые знания. Но не многие знают, какую информацию использовать и как. Именно для таких мы длительное время создавали рабочую методику, которая увеличит капитал любого. Она обеспечит финансовую стабильность и счастливое будущее. Это не сон, мы делимся этим с вами. Если вы желаете зарабатывать много и без усилий, будьте с нами! \r\n<b><a href=http://abreu.ru/kak-zarabotat-v-instagrame-yutub-100-000-tys-rublej-v-mesyats/>Как заработать в инстаграме ютуб 100 000 тыс. рублей в месяц....</a>\r\n</b>","name":"JepFleexy","email":"8e6bca4214ebb57140b5ccdb5447effe","website":"http://abreu.ru/","date":"2018-12-29T22:47:01.978Z"}