{"_id":"49e32560-d39d-11e9-985e-d7733b393af6","trap":"","parent":"","message":"Как быть \r\nкак думаете \r\nили тут \r\nхочу заказать \r\nметаллоизделия \r\nДелается тут или в другом месте искать   у метро \r\nрекламные буклетницы \r\nТакие фирмы это делают или я не правильно понимаю, нужно сделать а я вот выбираю и не могу понять,,, \r\nдверные ручки из металла \r\nэто же они могут сделать??? \r\nhttps://steelcentury.ru \r\nпока на них смотрю","name":"EverettZog","email":"534e736198cdea570e1eac4e6f435485","website":"https://steelcentury.ru","date":"2019-09-10T07:33:31.725Z"}