{"_id":"0a8682d0-6273-11ea-af0f-2b80f6e96fe2","trap":"","parent":"","message":"<a href=http://zinaidaaris.0bb.ru>заявка автомобильную перевозку груза</a> — это отличная альтернатива работы с диспетчерской. Наш сервис помогает находить клиентов, которым требуются услуги по перевозке грузов. http://zinaidaaris.mybb.by/viewtopic.php?id=6 \r\nhttp://zinaidaaris.mybb.by/viewtopic.php?id=9","name":"vykadan","email":"4edb138b5ee5336ca68df7ad8993dbfb","website":"http://zinaidaaris.mybb.ru","date":"2020-03-10T02:01:22.845Z"}