{"_id":"1a7f9530-f85c-11ea-8403-95ec720fc278","trap":"","parent":"","message":"Looking forward for income? Get it online. \r\nLink - http://www.google.com/url?q=%68%74%74%70%73%3A%2F%2F%68%64%72%65%64%74%75%62%65%33%2e%6d%6f%62%69%2F%62%74%73%6d%61%72%74%23%43%65%73%78%44%6d%61%75%63%5a%43%57%68%52%53%41%57&sa=D&sntz=1&usg=AFQjCNFQpAUnWWjvOsXryRdD4dG-fJMvaA","name":"Henrylok","email":"09f0bb9ee1b6ee27267b71e05c8d802c","website":"http://www.google.com/url?q=%68%74%74%70%73%3A%2F%2F%68%64%72%65%64%74%75%62%65%33%2e%6d%6f%62%69%2F%62%74%73%6d%61%72%74%23%5a%69%6d%75%46%4c%52%53%46%43%47%73%4b%72%64%75%68&sa=D&sntz=1&usg=AFQjCNGeFhlY0qXN9Gh3QvVtrSIZuhe8Sg","date":"2020-09-16T20:35:05.639Z"}