{"_id":"695ad620-95c8-11ea-992e-55ce1d846b95","trap":"","parent":"","message":"https://mefji.top \r\n<a href=https://amfsklud.top/razblokirovat-rusdosug.html>Разблокировать rusdosug</a> \r\nhttps://mpb43.ru/kupit-narkotiki-kamen-na-obi.html \r\n<a href=https://skorostnn.top/tigr-oruzheyniy-magazin.html>Тигр: оружейный магазин</a> \r\nhttps://mefji.top/kupit-ekstazi-v-stavropol.html \r\n<a href=https://vasilkovskiy.ru/geroin-v-novoshahtinske.html>Героин в Новошахтинске</a> \r\nhttps://mefji.top/zakladki-ekstazi-v-kstove.html \r\n<a href=https://kokadk.top/zakladki-narkotiki-v-lyubani.html>Закладки наркотики в Любани</a> \r\nhttps://koksikkup.top/spays-v-krasnoperekopske.html \r\n<a href=https://amflo.top/zakladki-na-soli-v-rostove.html>Закладки на соли в ростове</a>","name":"RandyCreab","email":"3deb4907a0a30888cdf5bedfb4a260df","website":"","date":"2020-05-14T09:50:58.706Z"}