{"_id":"1818e9f0-dcc7-11ea-b1ec-ff257b5e1a72","trap":"","parent":"","message":"https://hiforlikik.info/how-to-format-ssd-with-windows-on-it.html \r\n<a href=https://hiforlikik.info/binding-of-isaac-karma.html>binding of isaac karma</a> \r\nhttps://lovedownloads.info \r\n<a href=http://mail.switcodes.com/forum/viewtopic.php?f=7&t=5891&p=95594&sid=388f92520da1cb083ef00c5c9cef50c4#p95594>gta namaste america pc game download</a> \r\nhttp://zhuli.icoolcn.com/home.php?mod=space&uid=1794301 \r\nhttp://kotlasreg.ru/forum.php?PAGE_NAME=profile_view&UID=58647 \r\nhttps://vikelogym.info/mass-effect-3-nude.html \r\n<a href=http://www.0755pylt.com/forum.php?mod=viewthread&tid=9&pid=553741&page=223&extra=page%3D1#pid553741>kingdom come the good thief</a> \r\n<a href=https://hiforlikik.info/killer-instinct-pc-game-download.html>killer instinct pc game download</a> \r\nhttps://lowgreenpil.info \r\nhttp://wg-travel.com/index.php?option=com_k2&view=itemlist&task=user&id=1810737 \r\n<a href=http://principle.jp/bbs5/c-board.cgi?cmd=one;no=3512229;id=hijirin>terraria free downl</a> \r\nhttp://kotlasreg.ru/forum.php?PAGE_NAME=profile_view&UID=58657 \r\nhttps://lovedownloads.info/ben-10-alien-force-pc-game-download.html \r\n<a href=https://btc357.com/forum/viewtopic.php?pid=5957#p5957>the sims 4 mods mac</a> \r\n<a href=https://hiforlikik.info/download-mod-gta-5-ps3-offline.html>download mod gta 5 ps3 offline</a> \r\nhttps://blowjumpver.info \r\nhttp://haojiubujian.cc/space-uid-70129.html \r\n<a href=http://nsu-club.com/forum/viewtopic.php?f=10&t=1282679>microsoft outlook takes a long time to load</a> \r\nhttp://lyceum8.su/communication/forum/user/96703/ \r\nhttps://romenikstio.info/power-rangers-game-free-download.html \r\n<a href=https://hiforlikik.info/convert-studio-one-song-to-mp3.html>convert studio one song to mp3</a> \r\n<a href=http://forum.thedeschi.com/showthread.php?tid=32469&pid=217639#pid217639>fallout new vegas caravan deck</a> \r\nhttps://vikelogym.info \r\nhttps://igkpro.com/igk/profile.php?id=5830 \r\nhttp://l-avt.ru/support/dialog/?PAGE_NAME=profile_view&UID=18426 \r\n<a href=https://hralinks.info/viewtopic.php?f=8&t=21780>doom 2 weapon mod</a>","name":"Josephcar","email":"e9ee60afa452ba1d908bf4d5c38a01fc","website":"","date":"2020-08-12T18:10:25.242Z"}