{"_id":"56db12f0-2937-11eb-b07d-11e686dc6cdf","trap":"","parent":"","message":"ONLINE VERDIENEN VON 7065 EURO AM TAG - IN EINEM MONAT KONNEN SIE SICH EINE TEURE WOHNUNG KAUFEN: https://images.google.com.bz/url?q=https://shorturl.ac/70xqg \r\nPASSIVES EINKOMMEN ONLINE VOR 3765 EURO AM TAG - IN EINEM MONAT KONNEN SIE IHREN JOB SICHER KUNDIGEN: http://www.google.com.bn/url?q=https://onlineuniversalwork.com/3u0hb \r\nONLINE VERDIENEN VON 5776 EUR AM TAG - KEINE BERUFLICHEN FAHIGKEITEN: http://google.sn/url?q=http://asq.kr/r9T0AZROraaK8 \r\nPASSIVES EINKOMMEN ONLINE VON 6967 EURO PRO TAG - SIE WERDEN ALLE IHRE KREDITE IN EINER WOCHE ZURUCKZAHLEN: https://maps.google.com.lb/url?q=http://wunkit.com/rxcrAA \r\nPASSIVES EINKOMMEN ONLINE VOR 3768 EUR IN DER WOCHE - IN EINEM MONAT KONNEN SIE SICH EINE TEURE WOHNUNG KAUFEN: http://images.google.com.tw/url?q=https://shorturl.ac/70xqg \r\nPASSIVES EINKOMMEN IM INTERNET VON 3965 EURO AM TAG - DIE BESTE INVESTITIONSMOGLICHKEIT: https://www.google.bi/url?q=http://asq.kr/xmg698DtA4r9i \r\nONLINE VERDIENEN VOR 4757 EURO AM TAG - DIE BESTE SEITE, UM ONLINE GELD ZU VERDIENEN: http://maps.google.ml/url?q=https://slimex365.com/3ta40 \r\nONLINE VERDIENEN VOR 8068 EUR AM TAG - KEINE BERUFSERFAHRUNG: https://images.google.nl/url?q=https://darknesstr.com/3psnk \r\nPASSIVES EINKOMMEN VON 6848 EURO PRO TAG - SIE WERDEN ALLE IHRE KREDITE IN EINER WOCHE ZURUCKZAHLEN: https://maps.google.com.na/url?q=http://xsle.net/3sjzu \r\nPASSIVES EINKOMMEN VOR 9066 EURO IN DER WOCHE - DIE BESTE SEITE, UM ONLINE GELD ZU VERDIENEN: https://images.google.cv/url?q=https://onlineuniversalwork.com/3u0fx \r\nPASSIVES EINKOMMEN ONLINE VON 8848 EURO PRO TAG - IN EINEM MONAT KONNEN SIE IHREN JOB SICHER KUNDIGEN: http://images.google.com.gh/url?q=http://freeurlredirect.com/3vq9i \r\nEINNAHMEN IM INTERNET VOR 6078 EURO AM TAG - INNERHALB EINER WOCHE SIND SIE FINANZIELL UNABHANGIG: http://google.com.sl/url?q=https://links.wtf/xf8B \r\nPASSIVES EINKOMMEN IM INTERNET VON 7057 EUR IN DER WOCHE - IN EINEM MONAT KONNEN SIE IHREN JOB SICHER KUNDIGEN: http://www.google.com.vn/url?q=http://xsle.net/3sk24 \r\nPASSIVES EINKOMMEN ONLINE VON 8745 EURO AM TAG - INNERHALB EINER WOCHE SIND SIE FINANZIELL UNABHANGIG: https://www.google.com.cu/url?q=https://links.wtf/6ALn \r\nPASSIVES EINKOMMEN IM INTERNET VOR 6945 EURO PRO TAG - DIE BESTE SEITE, UM ONLINE GELD ZU VERDIENEN: https://google.bf/url?q=http://asq.kr/nOWwwBBG9fEY4 \r\nPASSIVES EINKOMMEN IM INTERNET VOR 9847 EURO AM TAG - IN EINEM MONAT KONNEN SIE SICH EIN TEURES HAUS KAUFEN: https://images.google.co.in/url?q=http://xsle.net/3sjy0 \r\nPASSIVES EINKOMMEN VOR 9865 EURO PRO TAG - IN EINEM MONAT KONNEN SIE SICH EINE TEURE WOHNUNG KAUFEN: http://www.google.se/url?q=https://qspark.me/LUJlHg \r\nPASSIVES EINKOMMEN IM INTERNET VON 7866 EUR IN DER WOCHE - INNERHALB EINER WOCHE SIND SIE FINANZIELL UNABHANGIG: http://google.com.cu/url?q=https://links.wtf/Xohi \r\nPASSIVES EINKOMMEN ONLINE VOR 4746 EURO PRO TAG - IN EINEM MONAT KONNEN SIE IHREN JOB SICHER KUNDIGEN: http://duck.com/url?q=http://wunkit.com/bRcrAA \r\nEINNAHMEN IM INTERNET VON 8757 EURO PRO TAG - GONNEN SIE SICH FINANZIELLE FREIHEIT: https://maps.google.com.bz/url?q=https://links.wtf/Xohi \r\nONLINE VERDIENEN VON 3076 EURO IN DER WOCHE - IN EINEM MONAT KONNEN SIE IHREN JOB SICHER KUNDIGEN: http://maps.google.com.gh/url?q=https://ecuadortenisclub.com/3qlzy \r\nPASSIVES EINKOMMEN VOR 9757 EURO PRO TAG - INNERHALB EINER WOCHE SIND SIE FINANZIELL UNABHANGIG: https://maps.google.com.fj/url?q=https://qspark.me/N1Yi7Y \r\nONLINE VERDIENEN VOR 5057 EURO IN DER WOCHE - KEINE BERUFSERFAHRUNG: http://maps.google.ht/url?q=https://ecuadortenisclub.com/3qlx4 \r\nPASSIVES EINKOMMEN IM INTERNET VON 3867 EURO AM TAG - KEINE BERUFSERFAHRUNG: https://www.google.lt/url?q=https://qspark.me/c0voIa \r\nPASSIVES EINKOMMEN ONLINE VON 9968 EURO IN DER WOCHE - SIE WERDEN ALLE IHRE KREDITE IN EINER WOCHE ZURUCKZAHLEN: https://google.com.nf/url?q=http://wunkit.com/KBcrAA","name":"RussellRuT","email":"e993501ff07e4174b84aca8bf31c4005","website":"","date":"2020-11-18T00:45:22.517Z"}