{"_id":"e758fae0-97d4-11e9-a7e3-717941eb3c30","trap":"","parent":"","message":"I really want to fuck myself in the ass on the camera!!!! \r\nI'm waiting for you!! \r\nand my ass wants to fuck! \r\n \r\nhttp://gg.gg/kenia/ - http://skype.miss-bdsm.mcdir.ru/img/77.jpg|http://gg.gg/kenia/ -  \r\nMy cunt is always wet mmm .... \r\nhttp://skype.miss-bdsm.mcdir.ru/img/21.jpg|http://gg.gg/kenia/ -  \r\n \r\nRegister and write me my nickname Xenia21 \r\nLink to my free webcam \r\nhttp://gg.gg/kenia/","name":"Sherrilex","email":"0b74423b9fa05a872388aed9b3ee0de6","website":"http://miss-bdsm.mcdir.ru/","date":"2019-06-26T05:40:28.570Z"}